<?xml version="1.0" encoding="utf-8" ?><dwsync><file name=".DS_Store" server="ftp.juliesonne.dk//" local="3627366190" remote="3627539940" Dst="-1" /><file name="flow1rapport.pdf" server="ftp.juliesonne.dk//" local="3627365761" remote="3627539940" Dst="-1" /><file name="flowfourdesignproces.pdf" server="ftp.juliesonne.dk//" local="3626948714" remote="3627540000" Dst="-1" /><file name="flowfourprojektstrykturering.pdf" server="ftp.juliesonne.dk//" local="3626949439" remote="3627540000" Dst="-1" /><file name="flowfourtestning.pdf" server="ftp.juliesonne.dk//" local="3626950905" remote="3627540000" Dst="-1" /><file name="flowthreekortsortering.pdf" server="ftp.juliesonne.dk//" local="3626942633" remote="3627540000" Dst="-1" /><file name="flowthreepersonastwo.pdf" server="ftp.juliesonne.dk//" local="3626941333" remote="3627540060" Dst="-1" /><file name="flowthreedesignproces_compressed.pdf" server="ftp.juliesonne.dk//" local="3626861808" remote="3627540120" Dst="-1" /><file name="MULA-07-sweetbot (2).pdf" server="ftp.juliesonne.dk//" local="3626083136" remote="3627540180" Dst="-1" /><file name="julie_sonne_bygenapp.pdf" server="ftp.juliesonne.dk//" local="3627366014" remote="3627540120" Dst="-1" /><file name="bygapp_juliesonne.pdf" server="ftp.juliesonne.dk//" local="3627366186" remote="3627540120" Dst="-1" /><file name="procesbillederportfolio.pdf" server="ftp.juliesonne.dk//" local="3627455819" remote="3627540180" Dst="-1" /></dwsync>